{
  "file-explorer:new-file": [
    {
      "modifiers": [
        "Alt"
      ],
      "key": "N"
    }
  ],
  "templater-obsidian:create-new-note-from-template": [
    {
      "modifiers": [
        "Mod"
      ],
      "key": "N"
    }
  ],
  "app:delete-file": [
    {
      "modifiers": [
        "Alt"
      ],
      "key": "D"
    }
  ],
  "file-explorer:new-folder": [
    {
      "modifiers": [
        "Alt",
        "Shift"
      ],
      "key": "F"
    }
  ],
  "workspace:split-vertical": [
    {
      "modifiers": [
        "Alt",
        "Shift"
      ],
      "key": "ArrowRight"
    }
  ],
  "app:toggle-left-sidebar": [
    {
      "modifiers": [
        "Alt"
      ],
      "key": "F"
    }
  ],
  "app:go-back": [
    {
      "modifiers": [
        "Alt"
      ],
      "key": "I"
    }
  ],
  "app:go-forward": [
    {
      "modifiers": [
        "Alt"
      ],
      "key": "O"
    }
  ],
  "editor:insert-codeblock": [
    {
      "modifiers": [
        "Alt"
      ],
      "key": "A"
    }
  ],
  "markdown:toggle-preview": [
    {
      "modifiers": [
        "Alt"
      ],
      "key": "S"
    }
  ],
  "execute-code:run-all-code-blocks-in-file": [
    {
      "modifiers": [
        "Alt"
      ],
      "key": ","
    }
  ]
}